func_gen/__init__.py
func_gen/eval.wasm
extism_func_gen-0.4.0.dist-info/METADATA
extism_func_gen-0.4.0.dist-info/WHEEL
extism_func_gen-0.4.0.dist-info/entry_points.txt
extism_func_gen-0.4.0.dist-info/RECORD
