Metadata-Version: 2.1
Name: extism-func-gen
Version: 0.4.0
Summary: 
License: MIT
Author: The Extism Authors
Author-email: oss@extism.org
Requires-Python: >=3.11,<4.0
Classifier: License :: OSI Approved :: MIT License
Classifier: Programming Language :: Python :: 3
Classifier: Programming Language :: Python :: 3.11
Requires-Dist: extism (>=0.3.0,<0.4.0)
Requires-Dist: langchain (>=0.0.150,<0.0.151)
Requires-Dist: openai (>=0.27.4,<0.28.0)
